    {
    	"deviceType" : "localmobileweb",
        "deviceClass" : "ipad",
        "manufacturer":"Apple",
        "osVersion" : "10.2",
        "os" : "iOS",
        "deviceName" : "iPad Air 2 Simulator",
        "driverProvider" : "LOCAL_IOS_MW",
        "factoryConfigKey" : "WEBTABLET",
        "caps" : {
          "platformName" : "iOS",
          "platformVersion" : "10.2",
          "deviceName" : "iPad Air 2",
          "automationName" : "XCUITest",
          "browserName" : "Safari",
          "autoAcceptAlerts" : "true"
    	}
    }
